mlflow_slurm/__init__.py
mlflow_slurm/slurm_backend.py
mlflow_slurm/templates/__init__.py
mlflow_slurm/templates/sbatch_template.sh
mlflow_slurm-1.0.6.dist-info/LICENSE
mlflow_slurm-1.0.6.dist-info/METADATA
mlflow_slurm-1.0.6.dist-info/WHEEL
mlflow_slurm-1.0.6.dist-info/entry_points.txt
mlflow_slurm-1.0.6.dist-info/top_level.txt
mlflow_slurm-1.0.6.dist-info/RECORD
