Metadata-Version: 2.1
Name: mlflow-slurm
Version: 1.0.6
Summary: Backend implementation for running MLFlow projects on Slurm
Home-page: https://github.com/ncsa/mlflow-slurm
Maintainer: Ben Galewsky
Maintainer-email: bengal1@illinois.edu
Keywords: mlflow
Classifier: Development Status :: 4 - Beta
Classifier: Intended Audience :: Developers
Classifier: Intended Audience :: Science/Research
Classifier: Operating System :: OS Independent
Classifier: License :: OSI Approved :: Apache Software License
Classifier: Programming Language :: Python :: 3
Classifier: Programming Language :: Python :: 3.6
Classifier: Programming Language :: Python :: 3.7
Classifier: Programming Language :: Python :: 3.8
Classifier: Programming Language :: Python :: 3.9
Classifier: Topic :: Software Development :: Libraries
Requires-Python: >=3.6
License-File: LICENSE
Requires-Dist: mlflow-skinny
Requires-Dist: jinja2
